cranelog-0.2.0.dist-info/METADATA
cranelog-0.2.0.dist-info/WHEEL
cranelog-0.2.0.dist-info/entry_points.txt
cranelog/__init__.py
cranelog/colors.py
cranelog/levels.py
cranelog/logger.py
cranelog-0.2.0.dist-info/RECORD
