Metadata-Version: 2.1
Name: cranelog
Version: 0.2.0
Summary: A modern colorful logging library for Python with rich context information
Keywords: logging,colorful,terminal,debug
Author-Email: weizhang124 <weizhang124@iflytek.com>
License: MIT
Classifier: Development Status :: 4 - Beta
Classifier: Environment :: Console
Classifier: Intended Audience :: Developers
Classifier: License :: OSI Approved :: MIT License
Classifier: Operating System :: OS Independent
Classifier: Programming Language :: Python :: 3
Classifier: Programming Language :: Python :: 3.10
Classifier: Programming Language :: Python :: 3.11
Classifier: Programming Language :: Python :: 3.12
Classifier: Topic :: Software Development :: Libraries :: Python Modules
Classifier: Topic :: System :: Logging
Project-URL: Homepage, https://github.com/weizhang124/cranelog
Project-URL: Repository, https://github.com/weizhang124/cranelog
Requires-Python: >=3.10
